{"partyMembers":[{"name":"Antoniooooo","status":"dead","disease":"dysentery"},{"name":"The sleeper","status":"dead","disease":"dysentery"},{"name":"Nick pic","status":"well","disease":""},{"name":"Colin","status":"well","disease":""},{"name":"Brady","status":"dead","disease":"influenza"},{"name":"the Tickler","status":"well","disease":""},{"name":"Keg Hurler","status":"well","disease":""}],"supplies":{"oxen":2,"setsClothing":3,"bullet":279,"wagonWheels":6,"wagonTongues":4,"wagonAxels":2,"poundsFood":184},"recentlyRecovered":"","recentlyDeceased":"","recentlyFellIll":"","locations":[{"name":"Rachel's Death Valley","source":"a.png"},{"name":"Brady's Terranium","source":"b.png"},{"name":"nicks's Terranium","source":"b.png"},{"name":"alex's Terranium","source":"b.png"},{"name":"antonio's Terranium","source":"b.png"},{"name":"gabe's Terranium","source":"b.png"},{"name":"Brady's bungalow","source":"b.png"}],"daysSpent":111,"currentLocation":6,"diseases":[{"name":"cholera","chance":30},{"name":"dysentery","chance":20},{"name":"broken leg","chance":80},{"name":"broken arm","chance":60},{"name":"bitten by snake","chance":100},{"name":"influenza","chance":20},{"name":"spontaneous combustion","chance":5000}],"id":"1493327031307"}